ZhuomianYunweiGuanliZhinan/README.md
ZhuomianYunweiGuanliZhinan/__init__.py
ZhuomianYunweiGuanliZhinan/__main__.py
ZhuomianYunweiGuanliZhinan/file.epub
ZhuomianYunweiGuanliZhinan/index.html
ZhuomianYunweiGuanliZhinan/css/__init__.py
ZhuomianYunweiGuanliZhinan/css/annotations.css
ZhuomianYunweiGuanliZhinan/css/main.css
ZhuomianYunweiGuanliZhinan/css/normalize.css
ZhuomianYunweiGuanliZhinan/css/popup.css
ZhuomianYunweiGuanliZhinan/font/__init__.py
ZhuomianYunweiGuanliZhinan/font/fontello.eot
ZhuomianYunweiGuanliZhinan/font/fontello.svg
ZhuomianYunweiGuanliZhinan/font/fontello.ttf
ZhuomianYunweiGuanliZhinan/font/fontello.woff
ZhuomianYunweiGuanliZhinan/img/__init__.py
ZhuomianYunweiGuanliZhinan/img/annotator-glyph-sprite.png
ZhuomianYunweiGuanliZhinan/img/annotator-icon-sprite.png
ZhuomianYunweiGuanliZhinan/img/apple-touch-icon.png
ZhuomianYunweiGuanliZhinan/img/cancelfullscreen.png
ZhuomianYunweiGuanliZhinan/img/close.png
ZhuomianYunweiGuanliZhinan/img/fullscreen.png
ZhuomianYunweiGuanliZhinan/img/loader.gif
ZhuomianYunweiGuanliZhinan/img/menu-icon.png
ZhuomianYunweiGuanliZhinan/img/save.png
ZhuomianYunweiGuanliZhinan/img/saved.png
ZhuomianYunweiGuanliZhinan/img/settings-s.png
ZhuomianYunweiGuanliZhinan/img/settings.png
ZhuomianYunweiGuanliZhinan/img/star.png
ZhuomianYunweiGuanliZhinan/js/__init__.py
ZhuomianYunweiGuanliZhinan/js/epub.js
ZhuomianYunweiGuanliZhinan/js/epub.min.js
ZhuomianYunweiGuanliZhinan/js/epub.min.map
ZhuomianYunweiGuanliZhinan/js/hooks.min.js
ZhuomianYunweiGuanliZhinan/js/hooks.min.map
ZhuomianYunweiGuanliZhinan/js/reader.js
ZhuomianYunweiGuanliZhinan/js/reader.js.map
ZhuomianYunweiGuanliZhinan/js/reader.min.js
ZhuomianYunweiGuanliZhinan/js/reader.min.map
ZhuomianYunweiGuanliZhinan/js/hooks/__init__.py
ZhuomianYunweiGuanliZhinan/js/hooks/extensions/__init__.py
ZhuomianYunweiGuanliZhinan/js/hooks/extensions/highlight.js
ZhuomianYunweiGuanliZhinan/js/libs/__init__.py
ZhuomianYunweiGuanliZhinan/js/libs/jquery.min.js
zhuomian_yunwei_guanli_zhinan-2024.3.5.0.dist-info/METADATA
zhuomian_yunwei_guanli_zhinan-2024.3.5.0.dist-info/WHEEL
zhuomian_yunwei_guanli_zhinan-2024.3.5.0.dist-info/entry_points.txt
zhuomian_yunwei_guanli_zhinan-2024.3.5.0.dist-info/top_level.txt
zhuomian_yunwei_guanli_zhinan-2024.3.5.0.dist-info/RECORD
